{"schemaVersion":1,"generatedAt":"2026-07-13T13:41:48.659Z","entries":[{"genre":"Roleplay & Avatar Sim","gameCount":189,"totalPlaying":1327625,"saturationScore":27,"whiteSpace":true,"components":{"hhi":0.2719645612247351,"top1Share":0.44187552961114773,"top3Share":0.7476124658695038,"incumbencyScore":1,"intensityScore":0.9870978130709075,"playersPerGame":7024.4708994709},"reason":null},{"genre":"Entertainment","gameCount":10,"totalPlaying":6366,"saturationScore":27,"whiteSpace":true,"components":{"hhi":0.1915150872690085,"top1Share":0.29940307885642475,"top3Share":0.6454602576185988,"incumbencyScore":0.5,"intensityScore":0.19377439720594763,"playersPerGame":636.6},"reason":null},{"genre":"Shopping","gameCount":15,"totalPlaying":107082,"saturationScore":25,"whiteSpace":true,"components":{"hhi":0.6237493646657454,"top1Share":0.7800470667339049,"top3Share":0.9319773631422648,"incumbencyScore":0.30000000000000004,"intensityScore":0.9883475541549586,"playersPerGame":7138.8},"reason":null},{"genre":"Puzzle","gameCount":18,"totalPlaying":7573,"saturationScore":24,"whiteSpace":true,"components":{"hhi":0.265484178826594,"top1Share":0.443681500066024,"top3Share":0.7759144328535587,"incumbencyScore":0.19999999999999996,"intensityScore":0.1651454771929452,"playersPerGame":420.72222222222223},"reason":null},{"genre":"Action","gameCount":209,"totalPlaying":536995,"saturationScore":22,"whiteSpace":true,"components":{"hhi":0.1364793670532863,"top1Share":0.35706291492472,"top3Share":0.44463542491084646,"incumbencyScore":0.7,"intensityScore":0.5788447338960708,"playersPerGame":2569.354066985646},"reason":null},{"genre":"Strategy","gameCount":51,"totalPlaying":93669,"saturationScore":19,"whiteSpace":true,"components":{"hhi":0.10680758322126163,"top1Share":0.25598650567423586,"top3Share":0.4859345140868377,"incumbencyScore":0.6,"intensityScore":0.4150798173985696,"playersPerGame":1836.6470588235295},"reason":null},{"genre":"RPG","gameCount":66,"totalPlaying":476900,"saturationScore":18,"whiteSpace":true,"components":{"hhi":0.43719866837623517,"top1Share":0.6551247641014888,"top3Share":0.7512749003984064,"incumbencyScore":0.4,"intensityScore":0.9892172904431942,"playersPerGame":7225.757575757576},"reason":null},{"genre":"Obby & Platformer","gameCount":220,"totalPlaying":343444,"saturationScore":17,"whiteSpace":true,"components":{"hhi":0.023930636278165884,"top1Share":0.0937678340573718,"top3Share":0.20799606340480545,"incumbencyScore":0.7,"intensityScore":0.3562699369922196,"playersPerGame":1561.1090909090908},"reason":null},{"genre":"Sports & Racing","gameCount":76,"totalPlaying":99796,"saturationScore":17,"whiteSpace":true,"components":{"hhi":0.16127474258879357,"top1Share":0.37267024730450116,"top3Share":0.5183875105214638,"incumbencyScore":0.30000000000000004,"intensityScore":0.3067545675296584,"playersPerGame":1313.1052631578948},"reason":null},{"genre":"Social","gameCount":25,"totalPlaying":44469,"saturationScore":15,"whiteSpace":true,"components":{"hhi":0.19124904801572543,"top1Share":0.3725966403562032,"top3Share":0.6448762058962423,"incumbencyScore":0.30000000000000004,"intensityScore":0.40245906513655666,"playersPerGame":1778.76},"reason":null},{"genre":"Shooter","gameCount":94,"totalPlaying":125881,"saturationScore":13,"whiteSpace":true,"components":{"hhi":0.0409091585747509,"top1Share":0.10959557041968208,"top3Share":0.2721300275657168,"incumbencyScore":0.5,"intensityScore":0.3117758008160207,"playersPerGame":1339.159574468085},"reason":null},{"genre":"Party & Casual","gameCount":91,"totalPlaying":233309,"saturationScore":10,"whiteSpace":true,"components":{"hhi":0.1206999759455744,"top1Share":0.32282509461701003,"top3Share":0.4554174935386119,"incumbencyScore":0.4,"intensityScore":0.5776304443704092,"playersPerGame":2563.835164835165},"reason":null},{"genre":"Survival","gameCount":233,"totalPlaying":931745,"saturationScore":8,"whiteSpace":true,"components":{"hhi":0.10535836099649733,"top1Share":0.30704967560866975,"top3Share":0.40499170910495896,"incumbencyScore":0.6,"intensityScore":0.8330991373020776,"playersPerGame":3998.9055793991415},"reason":null},{"genre":"Simulation","gameCount":733,"totalPlaying":1692301,"saturationScore":6,"whiteSpace":true,"components":{"hhi":0.022089123690031603,"top1Share":0.12360389788814165,"top3Share":0.18818283508666603,"incumbencyScore":0.5,"intensityScore":0.5207141212672058,"playersPerGame":2308.7326057298774},"reason":null},{"genre":"","gameCount":23,"totalPlaying":104713,"saturationScore":4,"whiteSpace":true,"components":{"hhi":0.3887993094211789,"top1Share":0.6077564390285829,"top3Share":0.7607173894358866,"incumbencyScore":0,"intensityScore":0.8916215953972497,"playersPerGame":4552.739130434783},"reason":null},{"genre":"Adventure","gameCount":115,"totalPlaying":244369,"saturationScore":2,"whiteSpace":true,"components":{"hhi":0.10044586569911164,"top1Share":0.2313182113934255,"top3Share":0.4791647058342097,"incumbencyScore":0.19999999999999996,"intensityScore":0.479285878732794,"playersPerGame":2124.9478260869564},"reason":null},{"genre":"Utility & Other","gameCount":1,"totalPlaying":1613,"saturationScore":null,"whiteSpace":false,"components":{"hhi":0,"top1Share":0,"top3Share":0,"incumbencyScore":null,"intensityScore":0,"playersPerGame":1613},"reason":"insufficient_games"},{"genre":"Education","gameCount":1,"totalPlaying":461,"saturationScore":null,"whiteSpace":false,"components":{"hhi":0,"top1Share":0,"top3Share":0,"incumbencyScore":null,"intensityScore":0,"playersPerGame":461},"reason":"insufficient_games"}]}
